odoo/addons/purchase_order_ubl_py3o/README.rst
odoo/addons/purchase_order_ubl_py3o/__init__.py
odoo/addons/purchase_order_ubl_py3o/__manifest__.py
odoo/addons/purchase_order_ubl_py3o/i18n/es.po
odoo/addons/purchase_order_ubl_py3o/i18n/purchase_order_ubl_py3o.pot
odoo/addons/purchase_order_ubl_py3o/models/__init__.py
odoo/addons/purchase_order_ubl_py3o/models/py3o_report.py
odoo/addons/purchase_order_ubl_py3o/readme/CONFIGURE.rst
odoo/addons/purchase_order_ubl_py3o/readme/CONTRIBUTORS.rst
odoo/addons/purchase_order_ubl_py3o/readme/DESCRIPTION.rst
odoo/addons/purchase_order_ubl_py3o/static/description/icon.png
odoo/addons/purchase_order_ubl_py3o/static/description/index.html
odoo14_addon_purchase_order_ubl_py3o-14.0.1.1.0.dist-info/METADATA
odoo14_addon_purchase_order_ubl_py3o-14.0.1.1.0.dist-info/WHEEL
odoo14_addon_purchase_order_ubl_py3o-14.0.1.1.0.dist-info/top_level.txt
odoo14_addon_purchase_order_ubl_py3o-14.0.1.1.0.dist-info/RECORD
