Metadata-Version: 2.1
Name: odoo14-addon-purchase-order-ubl-py3o
Version: 14.0.1.1.0
Summary: Generate UBL purchase orders with Py3o reporting engine
Home-page: https://github.com/OCA/edi
Author: Akretion,Odoo Community Association (OCA)
Author-email: support@odoo-community.org
License: AGPL-3
Platform: UNKNOWN
Classifier: Programming Language :: Python
Classifier: Framework :: Odoo
Classifier: Framework :: Odoo :: 14.0
Classifier: License :: OSI Approved :: GNU Affero General Public License v3
Requires-Python: >=3.6
Requires-Dist: odoo14-addon-purchase-order-ubl
Requires-Dist: odoo14-addon-report-py3o-fusion-server
Requires-Dist: odoo (<14.1dev,>=14.0a)
